{
    "/js/app.js": "/js/app.js",
    "/css/app.css": "/css/app.css",
    "/css/semantic.min.css": "/css/semantic.min.css",
    "/js/semantic.min.js": "/js/semantic.min.js",
    "/node_modules/tinymce/jquery.tinymce.js": "/node_modules/tinymce/jquery.tinymce.js",
    "/node_modules/tinymce/jquery.tinymce.min.js": "/node_modules/tinymce/jquery.tinymce.min.js",
    "/node_modules/tinymce/tinymce.js": "/node_modules/tinymce/tinymce.js",
    "/node_modules/tinymce/tinymce.min.js": "/node_modules/tinymce/tinymce.min.js"
}
